Vectorgrad/__init__.py
Vectorgrad/draw.py
Vectorgrad/engine.py
Vectorgrad/nn.py
Vectorgrad-0.0.1.dist-info/LICENSE
Vectorgrad-0.0.1.dist-info/METADATA
Vectorgrad-0.0.1.dist-info/WHEEL
Vectorgrad-0.0.1.dist-info/top_level.txt
Vectorgrad-0.0.1.dist-info/RECORD
