Metadata-Version: 2.1
Name: Vectorgrad
Version: 0.0.1
Summary: A lightweight autograd engine that supports tensor operations and gradients with a small, customizable neural network library on top
Home-page: https://github.com/Sina-Haz/VectorGrad
Author: Sina Hazeghi
Author-email: shazeghian@gmail.com
Classifier: Programming Language :: Python :: 3
Classifier: License :: OSI Approved :: MIT License
Classifier: Operating System :: OS Independent
Requires-Python: >=3.6
License-File: LICENSE
